tf_alloc/__init__.py
tf_alloc/allocate.py
tf_alloc/gpu.py
tf_alloc/utils.py
tf_alloc-0.0.3.dist-info/LICENSE
tf_alloc-0.0.3.dist-info/METADATA
tf_alloc-0.0.3.dist-info/WHEEL
tf_alloc-0.0.3.dist-info/top_level.txt
tf_alloc-0.0.3.dist-info/RECORD
