Metadata-Version: 2.1
Name: tf-alloc
Version: 0.0.3
Summary: Simplication of GPU allocation for Tensorflow2
Home-page: https://github.com/KorKite/tf_alloc
Author: Kojunseo
Author-email: sta06167@naver.com
License: UNKNOWN
Platform: UNKNOWN
Classifier: License :: OSI Approved :: MIT License
License-File: LICENSE
